sqlfluff_easy_ql/LT01.py
sqlfluff_easy_ql/LT02.py
sqlfluff_easy_ql/__init__.py
sqlfluff_easy_ql/easy_ql_default_config.cfg
sqlfluff_easy_ql/rules.py
sqlfluff_plugin_easy_ql-0.1.2.dist-info/LICENSE
sqlfluff_plugin_easy_ql-0.1.2.dist-info/METADATA
sqlfluff_plugin_easy_ql-0.1.2.dist-info/WHEEL
sqlfluff_plugin_easy_ql-0.1.2.dist-info/entry_points.txt
sqlfluff_plugin_easy_ql-0.1.2.dist-info/top_level.txt
sqlfluff_plugin_easy_ql-0.1.2.dist-info/RECORD
